ler/__init__.py
ler/gw_source_population/__init__.py
ler/gw_source_population/cbc_source_parameter_distribution.py
ler/gw_source_population/cbc_source_redshift_distribution.py
ler/gw_source_population/jit_functions.py
ler/image_properties/__init__.py
ler/image_properties/image_properties.py
ler/image_properties/multiprocessing_routine.py
ler/lens_galaxy_population/__init__.py
ler/lens_galaxy_population/jit_functions.py
ler/lens_galaxy_population/lens_galaxy_parameter_distribution.py
ler/lens_galaxy_population/mp.py
ler/lens_galaxy_population/optical_depth.py
ler/rates/__init__.py
ler/rates/gwrates.py
ler/rates/ler copy.py
ler/rates/ler.py
ler/utils/__init__.py
ler/utils/plots.py
ler/utils/utils.py
ler-0.4.2.dist-info/LICENSE
ler-0.4.2.dist-info/METADATA
ler-0.4.2.dist-info/WHEEL
ler-0.4.2.dist-info/top_level.txt
ler-0.4.2.dist-info/RECORD
