Metadata-Version: 2.1
Name: ler
Version: 0.4.2
Summary: LVK (LIGO-Virgo-KAGRA collaboration) Event (compact-binary mergers) Rate calculator and simulator
Home-page: https://github.com/hemantaph/ler
Author: Hemantakumar
Author-email: hemantaphurailatpam@gmail.com
License: MIT
Requires-Python: >=3.10
License-File: LICENSE
Requires-Dist: setuptools >=65.5.0
Requires-Dist: matplotlib >=3.4.2
Requires-Dist: pycbc >=2.0.4
Requires-Dist: numpy >=1.18
Requires-Dist: numba >=0.57.1
Requires-Dist: bilby >=1.0.2
Requires-Dist: gwsnr >=0.3.2
Requires-Dist: scipy <1.14.0
Requires-Dist: lenstronomy >=1.10.4
Requires-Dist: astropy >=5.1
Requires-Dist: tqdm >=4.64.1
Requires-Dist: pointpats >=2.3
Requires-Dist: shapely >=2.0.1
Requires-Dist: gwcosmo ==2.1.0
